[
  {
    "CoaCode": null,
    "SortCode": 1,
    "Section": "Guarantees Issued",
    "RowDescription": "Guarantees Issued:",
    "RowType": "VAL",
    "SumType": null,
    "SumAccounts": null,
    "col1": 0,
    "col2": null,
    "col3": 0,
    "col4": null,
    "col5": 0
  },
  {
    "CoaCode": "8101 000",
    "SortCode": 2,
    "Section": "Guarantees Issued",
    "RowDescription": "Direct credit substitutes",
    "RowType": "VAL",
    "SumType": null,
    "SumAccounts": null,
    "col1": 0,
    "col2": null,
    "col3": 0,
    "col4": null,
    "col5": 0
  },
  {
    "CoaCode": "10",
    "SortCode": 3,
    "Section": "Guarantees Issued",
    "RowDescription": "with risk grade 1",
    "RowType": "VAL",
    "SumType": null,
    "SumAccounts": null,
    "col1": 0,
    "col2": null,
    "col3": 0,
    "col4": null,
    "col5": 0
  },
  {
    "CoaCode": "20",
    "SortCode": 4,
    "Section": "Guarantees Issued",
    "RowDescription": "with risk grade 2",
    "RowType": "VAL",
    "SumType": null,
    "SumAccounts": null,
    "col1": 0,
    "col2": null,
    "col3": 0,
    "col4": null,
    "col5": 0
  },
  {
    "CoaCode": "30",
    "SortCode": 5,
    "Section": "Guarantees Issued",
    "RowDescription": "with risk grade 3",
    "RowType": "VAL",
    "SumType": null,
    "SumAccounts": null,
    "col1": 0,
    "col2": null,
    "col3": 0,
    "col4": null,
    "col5": 0
  },
  {
    "CoaCode": "40",
    "SortCode": 6,
    "Section": "Guarantees Issued",
    "RowDescription": "with risk grade 4",
    "RowType": "VAL",
    "SumType": null,
    "SumAccounts": null,
    "col1": 0,
    "col2": null,
    "col3": 0,
    "col4": null,
    "col5": 0
  },
  {
    "CoaCode": "50",
    "SortCode": 7,
    "Section": "Guarantees Issued",
    "RowDescription": "with risk grade 5",
    "RowType": "VAL",
    "SumType": null,
    "SumAccounts": null,
    "col1": 0,
    "col2": null,
    "col3": 0,
    "col4": null,
    "col5": 0
  },
  {
    "CoaCode": "60",
    "SortCode": 8,
    "Section": "Guarantees Issued",
    "RowDescription": "with risk grade 6",
    "RowType": "VAL",
    "SumType": null,
    "SumAccounts": null,
    "col1": 0,
    "col2": null,
    "col3": 0,
    "col4": null,
    "col5": 0
  },
  {
    "CoaCode": "8102 000",
    "SortCode": 9,
    "Section": "Guarantees Issued",
    "RowDescription": "Standby Letters of Credit",
    "RowType": "VAL",
    "SumType": null,
    "SumAccounts": null,
    "col1": 0,
    "col2": null,
    "col3": 0,
    "col4": null,
    "col5": 0
  },
  {
    "CoaCode": "80",
    "SortCode": 10,
    "Section": "Guarantees Issued",
    "RowDescription": "with risk grade 1",
    "RowType": "VAL",
    "SumType": null,
    "SumAccounts": null,
    "col1": 0,
    "col2": null,
    "col3": 0,
    "col4": null,
    "col5": 0
  },
  {
    "CoaCode": "90",
    "SortCode": 11,
    "Section": "Guarantees Issued",
    "RowDescription": "with risk grade 2",
    "RowType": "VAL",
    "SumType": null,
    "SumAccounts": null,
    "col1": 0,
    "col2": null,
    "col3": 0,
    "col4": null,
    "col5": 0
  },
  {
    "CoaCode": "100",
    "SortCode": 12,
    "Section": "Guarantees Issued",
    "RowDescription": "with risk grade 3",
    "RowType": "VAL",
    "SumType": null,
    "SumAccounts": null,
    "col1": 0,
    "col2": null,
    "col3": 0,
    "col4": null,
    "col5": 0
  },
  {
    "CoaCode": "110",
    "SortCode": 13,
    "Section": "Guarantees Issued",
    "RowDescription": "with risk grade 4",
    "RowType": "VAL",
    "SumType": null,
    "SumAccounts": null,
    "col1": 0,
    "col2": null,
    "col3": 0,
    "col4": null,
    "col5": 0
  },
  {
    "CoaCode": "120",
    "SortCode": 14,
    "Section": "Guarantees Issued",
    "RowDescription": "with risk grade 5",
    "RowType": "VAL",
    "SumType": null,
    "SumAccounts": null,
    "col1": 0,
    "col2": null,
    "col3": 0,
    "col4": null,
    "col5": 0
  },
  {
    "CoaCode": "130",
    "SortCode": 15,
    "Section": "Guarantees Issued",
    "RowDescription": "with risk grade 6",
    "RowType": "VAL",
    "SumType": null,
    "SumAccounts": null,
    "col1": 0,
    "col2": null,
    "col3": 0,
    "col4": null,
    "col5": 0
  },
  {
    "CoaCode": "8103 000",
    "SortCode": 16,
    "Section": "Guarantees Issued",
    "RowDescription": "Short term; self liquidating trade letters",
    "RowType": "VAL",
    "SumType": null,
    "SumAccounts": null,
    "col1": 0,
    "col2": null,
    "col3": 0,
    "col4": null,
    "col5": 0
  },
  {
    "CoaCode": "150",
    "SortCode": 17,
    "Section": "Guarantees Issued",
    "RowDescription": "with risk grade 1",
    "RowType": "VAL",
    "SumType": null,
    "SumAccounts": null,
    "col1": 0,
    "col2": null,
    "col3": 0,
    "col4": null,
    "col5": 0
  },
  {
    "CoaCode": "160",
    "SortCode": 18,
    "Section": "Guarantees Issued",
    "RowDescription": "with risk grade 2",
    "RowType": "VAL",
    "SumType": null,
    "SumAccounts": null,
    "col1": 0,
    "col2": null,
    "col3": 0,
    "col4": null,
    "col5": 0
  },
  {
    "CoaCode": "170",
    "SortCode": 19,
    "Section": "Guarantees Issued",
    "RowDescription": "with risk grade 3",
    "RowType": "VAL",
    "SumType": null,
    "SumAccounts": null,
    "col1": 0,
    "col2": null,
    "col3": 0,
    "col4": null,
    "col5": 0
  },
  {
    "CoaCode": "180",
    "SortCode": 20,
    "Section": "Guarantees Issued",
    "RowDescription": "with risk grade 4",
    "RowType": "VAL",
    "SumType": null,
    "SumAccounts": null,
    "col1": 0,
    "col2": null,
    "col3": 0,
    "col4": null,
    "col5": 0
  },
  {
    "CoaCode": "190",
    "SortCode": 21,
    "Section": "Guarantees Issued",
    "RowDescription": "with risk grade 5",
    "RowType": "VAL",
    "SumType": null,
    "SumAccounts": null,
    "col1": 0,
    "col2": null,
    "col3": 0,
    "col4": null,
    "col5": 0
  },
  {
    "CoaCode": "200",
    "SortCode": 22,
    "Section": "Guarantees Issued",
    "RowDescription": "with risk grade 6",
    "RowType": "VAL",
    "SumType": null,
    "SumAccounts": null,
    "col1": 0,
    "col2": null,
    "col3": 0,
    "col4": null,
    "col5": 0
  },
  {
    "CoaCode": "8104 000",
    "SortCode": 23,
    "Section": "Guarantees Issued",
    "RowDescription": "Credit arising from the movement of goods",
    "RowType": "VAL",
    "SumType": null,
    "SumAccounts": null,
    "col1": 0,
    "col2": null,
    "col3": 0,
    "col4": null,
    "col5": 0
  },
  {
    "CoaCode": "220",
    "SortCode": 24,
    "Section": "Guarantees Issued",
    "RowDescription": "with risk grade 1",
    "RowType": "VAL",
    "SumType": null,
    "SumAccounts": null,
    "col1": 0,
    "col2": null,
    "col3": 0,
    "col4": null,
    "col5": 0
  },
  {
    "CoaCode": "230",
    "SortCode": 25,
    "Section": "Guarantees Issued",
    "RowDescription": "with risk grade 2",
    "RowType": "VAL",
    "SumType": null,
    "SumAccounts": null,
    "col1": 0,
    "col2": null,
    "col3": 0,
    "col4": null,
    "col5": 0
  },
  {
    "CoaCode": "240",
    "SortCode": 26,
    "Section": "Guarantees Issued",
    "RowDescription": "with risk grade 3",
    "RowType": "VAL",
    "SumType": null,
    "SumAccounts": null,
    "col1": 0,
    "col2": null,
    "col3": 0,
    "col4": null,
    "col5": 0
  },
  {
    "CoaCode": "250",
    "SortCode": 27,
    "Section": "Guarantees Issued",
    "RowDescription": "with risk grade 4",
    "RowType": "VAL",
    "SumType": null,
    "SumAccounts": null,
    "col1": 0,
    "col2": null,
    "col3": 0,
    "col4": null,
    "col5": 0
  },
  {
    "CoaCode": "260",
    "SortCode": 28,
    "Section": "Guarantees Issued",
    "RowDescription": "with risk grade 5",
    "RowType": "VAL",
    "SumType": null,
    "SumAccounts": null,
    "col1": 0,
    "col2": null,
    "col3": 0,
    "col4": null,
    "col5": 0
  },
  {
    "CoaCode": "270",
    "SortCode": 29,
    "Section": "Guarantees Issued",
    "RowDescription": "with risk grade 6",
    "RowType": "VAL",
    "SumType": null,
    "SumAccounts": null,
    "col1": 0,
    "col2": null,
    "col3": 0,
    "col4": null,
    "col5": 0
  },
  {
    "CoaCode": null,
    "SortCode": 30,
    "Section": "Risk Participations",
    "RowDescription": "Risk Participations:",
    "RowType": "VAL",
    "SumType": null,
    "SumAccounts": null,
    "col1": 0,
    "col2": null,
    "col3": 0,
    "col4": null,
    "col5": 0
  },
  {
    "CoaCode": "8201 000",
    "SortCode": 31,
    "Section": "Risk Participations",
    "RowDescription": "Risk participations in bankers acceptances",
    "RowType": "VAL",
    "SumType": null,
    "SumAccounts": null,
    "col1": 0,
    "col2": null,
    "col3": 0,
    "col4": null,
    "col5": 0
  },
  {
    "CoaCode": "300",
    "SortCode": 32,
    "Section": "Risk Participations",
    "RowDescription": "with risk grade 1",
    "RowType": "VAL",
    "SumType": null,
    "SumAccounts": null,
    "col1": 0,
    "col2": null,
    "col3": 0,
    "col4": null,
    "col5": 0
  },
  {
    "CoaCode": "310",
    "SortCode": 33,
    "Section": "Risk Participations",
    "RowDescription": "with risk grade 2",
    "RowType": "VAL",
    "SumType": null,
    "SumAccounts": null,
    "col1": 0,
    "col2": null,
    "col3": 0,
    "col4": null,
    "col5": 0
  },
  {
    "CoaCode": "320",
    "SortCode": 34,
    "Section": "Risk Participations",
    "RowDescription": "with risk grade 3",
    "RowType": "VAL",
    "SumType": null,
    "SumAccounts": null,
    "col1": 0,
    "col2": null,
    "col3": 0,
    "col4": null,
    "col5": 0
  },
  {
    "CoaCode": "330",
    "SortCode": 35,
    "Section": "Risk Participations",
    "RowDescription": "with risk grade 4",
    "RowType": "VAL",
    "SumType": null,
    "SumAccounts": null,
    "col1": 0,
    "col2": null,
    "col3": 0,
    "col4": null,
    "col5": 0
  },
  {
    "CoaCode": "340",
    "SortCode": 36,
    "Section": "Risk Participations",
    "RowDescription": "with risk grade 5",
    "RowType": "VAL",
    "SumType": null,
    "SumAccounts": null,
    "col1": 0,
    "col2": null,
    "col3": 0,
    "col4": null,
    "col5": 0
  },
  {
    "CoaCode": "350",
    "SortCode": 37,
    "Section": "Risk Participations",
    "RowDescription": "with risk grade 6",
    "RowType": "VAL",
    "SumType": null,
    "SumAccounts": null,
    "col1": 0,
    "col2": null,
    "col3": 0,
    "col4": null,
    "col5": 0
  },
  {
    "CoaCode": "8202 000",
    "SortCode": 38,
    "Section": "Risk Participations",
    "RowDescription": "Risk participations in financial standby letters of credit",
    "RowType": "VAL",
    "SumType": null,
    "SumAccounts": null,
    "col1": 0,
    "col2": null,
    "col3": 0,
    "col4": null,
    "col5": 0
  },
  {
    "CoaCode": "370",
    "SortCode": 39,
    "Section": "Risk Participations",
    "RowDescription": "with risk grade 1",
    "RowType": "VAL",
    "SumType": null,
    "SumAccounts": null,
    "col1": 0,
    "col2": null,
    "col3": 0,
    "col4": null,
    "col5": 0
  },
  {
    "CoaCode": "380",
    "SortCode": 40,
    "Section": "Risk Participations",
    "RowDescription": "with risk grade 2",
    "RowType": "VAL",
    "SumType": null,
    "SumAccounts": null,
    "col1": 0,
    "col2": null,
    "col3": 0,
    "col4": null,
    "col5": 0
  },
  {
    "CoaCode": "390",
    "SortCode": 41,
    "Section": "Risk Participations",
    "RowDescription": "with risk grade 3",
    "RowType": "VAL",
    "SumType": null,
    "SumAccounts": null,
    "col1": 0,
    "col2": null,
    "col3": 0,
    "col4": null,
    "col5": 0
  },
  {
    "CoaCode": "400",
    "SortCode": 42,
    "Section": "Risk Participations",
    "RowDescription": "with risk grade 4",
    "RowType": "VAL",
    "SumType": null,
    "SumAccounts": null,
    "col1": 0,
    "col2": null,
    "col3": 0,
    "col4": null,
    "col5": 0
  },
  {
    "CoaCode": "410",
    "SortCode": 43,
    "Section": "Risk Participations",
    "RowDescription": "with risk grade 5",
    "RowType": "VAL",
    "SumType": null,
    "SumAccounts": null,
    "col1": 0,
    "col2": null,
    "col3": 0,
    "col4": null,
    "col5": 0
  },
  {
    "CoaCode": "420",
    "SortCode": 44,
    "Section": "Risk Participations",
    "RowDescription": "with risk grade 6",
    "RowType": "VAL",
    "SumType": null,
    "SumAccounts": null,
    "col1": 0,
    "col2": null,
    "col3": 0,
    "col4": null,
    "col5": 0
  },
  {
    "CoaCode": null,
    "SortCode": 45,
    "Section": "Repo-Style Transactions",
    "RowDescription": "Repo-Style Transactions:",
    "RowType": "VAL",
    "SumType": null,
    "SumAccounts": null,
    "col1": 0,
    "col2": null,
    "col3": 0,
    "col4": null,
    "col5": 0
  },
  {
    "CoaCode": "8301 000",
    "SortCode": 46,
    "Section": "Repo-Style Transactions",
    "RowDescription": "Sale and repurchase agreements",
    "RowType": "VAL",
    "SumType": null,
    "SumAccounts": null,
    "col1": 0,
    "col2": null,
    "col3": 0,
    "col4": null,
    "col5": 0
  },
  {
    "CoaCode": "450",
    "SortCode": 47,
    "Section": "Repo-Style Transactions",
    "RowDescription": "with risk grade 1",
    "RowType": "VAL",
    "SumType": null,
    "SumAccounts": null,
    "col1": 0,
    "col2": null,
    "col3": 0,
    "col4": null,
    "col5": 0
  },
  {
    "CoaCode": "460",
    "SortCode": 48,
    "Section": "Repo-Style Transactions",
    "RowDescription": "with risk grade 2",
    "RowType": "VAL",
    "SumType": null,
    "SumAccounts": null,
    "col1": 0,
    "col2": null,
    "col3": 0,
    "col4": null,
    "col5": 0
  },
  {
    "CoaCode": "470",
    "SortCode": 49,
    "Section": "Repo-Style Transactions",
    "RowDescription": "with risk grade 3",
    "RowType": "VAL",
    "SumType": null,
    "SumAccounts": null,
    "col1": 0,
    "col2": null,
    "col3": 0,
    "col4": null,
    "col5": 0
  },
  {
    "CoaCode": "480",
    "SortCode": 50,
    "Section": "Repo-Style Transactions",
    "RowDescription": "with risk grade 4",
    "RowType": "VAL",
    "SumType": null,
    "SumAccounts": null,
    "col1": 0,
    "col2": null,
    "col3": 0,
    "col4": null,
    "col5": 0
  },
  {
    "CoaCode": "490",
    "SortCode": 51,
    "Section": "Repo-Style Transactions",
    "RowDescription": "with risk grade 5",
    "RowType": "VAL",
    "SumType": null,
    "SumAccounts": null,
    "col1": 0,
    "col2": null,
    "col3": 0,
    "col4": null,
    "col5": 0
  },
  {
    "CoaCode": "500",
    "SortCode": 52,
    "Section": "Repo-Style Transactions",
    "RowDescription": "with risk grade 6",
    "RowType": "VAL",
    "SumType": null,
    "SumAccounts": null,
    "col1": 12853375.93,
    "col2": null,
    "col3": 0,
    "col4": null,
    "col5": 0
  },
  {
    "CoaCode": "8302 000",
    "SortCode": 53,
    "Section": "Repo-Style Transactions",
    "RowDescription": "Assets sales with recourse",
    "RowType": "VAL",
    "SumType": null,
    "SumAccounts": null,
    "col1": 0,
    "col2": null,
    "col3": 0,
    "col4": null,
    "col5": 0
  },
  {
    "CoaCode": "520",
    "SortCode": 54,
    "Section": "Repo-Style Transactions",
    "RowDescription": "with risk grade 1",
    "RowType": "VAL",
    "SumType": null,
    "SumAccounts": null,
    "col1": 0,
    "col2": null,
    "col3": 0,
    "col4": null,
    "col5": 0
  },
  {
    "CoaCode": "530",
    "SortCode": 55,
    "Section": "Repo-Style Transactions",
    "RowDescription": "with risk grade 2",
    "RowType": "VAL",
    "SumType": null,
    "SumAccounts": null,
    "col1": 0,
    "col2": null,
    "col3": 0,
    "col4": null,
    "col5": 0
  },
  {
    "CoaCode": "540",
    "SortCode": 56,
    "Section": "Repo-Style Transactions",
    "RowDescription": "with risk grade 3",
    "RowType": "VAL",
    "SumType": null,
    "SumAccounts": null,
    "col1": 0,
    "col2": null,
    "col3": 0,
    "col4": null,
    "col5": 0
  },
  {
    "CoaCode": "550",
    "SortCode": 57,
    "Section": "Repo-Style Transactions",
    "RowDescription": "with risk grade 4",
    "RowType": "VAL",
    "SumType": null,
    "SumAccounts": null,
    "col1": 0,
    "col2": null,
    "col3": 0,
    "col4": null,
    "col5": 0
  },
  {
    "CoaCode": "560",
    "SortCode": 58,
    "Section": "Repo-Style Transactions",
    "RowDescription": "with risk grade 5",
    "RowType": "VAL",
    "SumType": null,
    "SumAccounts": null,
    "col1": 0,
    "col2": null,
    "col3": 0,
    "col4": null,
    "col5": 0
  },
  {
    "CoaCode": "570",
    "SortCode": 59,
    "Section": "Repo-Style Transactions",
    "RowDescription": "with risk grade 6",
    "RowType": "VAL",
    "SumType": null,
    "SumAccounts": null,
    "col1": 0,
    "col2": null,
    "col3": 0,
    "col4": null,
    "col5": 0
  },
  {
    "CoaCode": "8303 000",
    "SortCode": 60,
    "Section": "Repo-Style Transactions",
    "RowDescription": "Lending of banks' securities or posting of securities as collateral",
    "RowType": "VAL",
    "SumType": null,
    "SumAccounts": null,
    "col1": 0,
    "col2": null,
    "col3": 0,
    "col4": null,
    "col5": 0
  },
  {
    "CoaCode": "590",
    "SortCode": 61,
    "Section": "Repo-Style Transactions",
    "RowDescription": "with risk grade 1",
    "RowType": "VAL",
    "SumType": null,
    "SumAccounts": null,
    "col1": 0,
    "col2": null,
    "col3": 0,
    "col4": null,
    "col5": 0
  },
  {
    "CoaCode": "600",
    "SortCode": 62,
    "Section": "Repo-Style Transactions",
    "RowDescription": "with risk grade 2",
    "RowType": "VAL",
    "SumType": null,
    "SumAccounts": null,
    "col1": 0,
    "col2": null,
    "col3": 0,
    "col4": null,
    "col5": 0
  },
  {
    "CoaCode": "610",
    "SortCode": 63,
    "Section": "Repo-Style Transactions",
    "RowDescription": "with risk grade 3",
    "RowType": "VAL",
    "SumType": null,
    "SumAccounts": null,
    "col1": 0,
    "col2": null,
    "col3": 0,
    "col4": null,
    "col5": 0
  },
  {
    "CoaCode": "620",
    "SortCode": 64,
    "Section": "Repo-Style Transactions",
    "RowDescription": "with risk grade 4",
    "RowType": "VAL",
    "SumType": null,
    "SumAccounts": null,
    "col1": 0,
    "col2": null,
    "col3": 0,
    "col4": null,
    "col5": 0
  },
  {
    "CoaCode": "630",
    "SortCode": 65,
    "Section": "Repo-Style Transactions",
    "RowDescription": "with risk grade 5",
    "RowType": "VAL",
    "SumType": null,
    "SumAccounts": null,
    "col1": 0,
    "col2": null,
    "col3": 0,
    "col4": null,
    "col5": 0
  },
  {
    "CoaCode": "640",
    "SortCode": 66,
    "Section": "Repo-Style Transactions",
    "RowDescription": "with risk grade 6",
    "RowType": "VAL",
    "SumType": null,
    "SumAccounts": null,
    "col1": 0,
    "col2": null,
    "col3": 0,
    "col4": null,
    "col5": 0
  },
  {
    "CoaCode": null,
    "SortCode": 67,
    "Section": "Note Issuance Facilities and Revolving Underwriting Facilities",
    "RowDescription": "Note Issuance Facilities and Revolving Underwriting Facilities",
    "RowType": "VAL",
    "SumType": null,
    "SumAccounts": null,
    "col1": 0,
    "col2": null,
    "col3": 0,
    "col4": null,
    "col5": 0
  },
  {
    "CoaCode": "670",
    "SortCode": 68,
    "Section": "Note Issuance Facilities and Revolving Underwriting Facilities",
    "RowDescription": "with risk grade 1",
    "RowType": "VAL",
    "SumType": null,
    "SumAccounts": null,
    "col1": 0,
    "col2": null,
    "col3": 0,
    "col4": null,
    "col5": 0
  },
  {
    "CoaCode": "680",
    "SortCode": 69,
    "Section": "Note Issuance Facilities and Revolving Underwriting Facilities",
    "RowDescription": "with risk grade 2",
    "RowType": "VAL",
    "SumType": null,
    "SumAccounts": null,
    "col1": 0,
    "col2": null,
    "col3": 0,
    "col4": null,
    "col5": 0
  },
  {
    "CoaCode": "690",
    "SortCode": 70,
    "Section": "Note Issuance Facilities and Revolving Underwriting Facilities",
    "RowDescription": "with risk grade 3",
    "RowType": "VAL",
    "SumType": null,
    "SumAccounts": null,
    "col1": 0,
    "col2": null,
    "col3": 0,
    "col4": null,
    "col5": 0
  },
  {
    "CoaCode": "700",
    "SortCode": 71,
    "Section": "Note Issuance Facilities and Revolving Underwriting Facilities",
    "RowDescription": "with risk grade 4",
    "RowType": "VAL",
    "SumType": null,
    "SumAccounts": null,
    "col1": 0,
    "col2": null,
    "col3": 0,
    "col4": null,
    "col5": 0
  },
  {
    "CoaCode": "710",
    "SortCode": 72,
    "Section": "Note Issuance Facilities and Revolving Underwriting Facilities",
    "RowDescription": "with risk grade 5",
    "RowType": "VAL",
    "SumType": null,
    "SumAccounts": null,
    "col1": 0,
    "col2": null,
    "col3": 0,
    "col4": null,
    "col5": 0
  },
  {
    "CoaCode": "720",
    "SortCode": 73,
    "Section": "Note Issuance Facilities and Revolving Underwriting Facilities",
    "RowDescription": "with risk grade 6",
    "RowType": "VAL",
    "SumType": null,
    "SumAccounts": null,
    "col1": 0,
    "col2": null,
    "col3": 0,
    "col4": null,
    "col5": 0
  },
  {
    "CoaCode": "8500 000",
    "SortCode": 74,
    "Section": "Commitments",
    "RowDescription": "Commitments",
    "RowType": "VAL",
    "SumType": null,
    "SumAccounts": null,
    "col1": 0,
    "col2": null,
    "col3": 0,
    "col4": null,
    "col5": 0
  },
  {
    "CoaCode": "8501 000",
    "SortCode": 75,
    "Section": "Commitments",
    "RowDescription": "Forward asset purchases",
    "RowType": "VAL",
    "SumType": null,
    "SumAccounts": null,
    "col1": 0,
    "col2": null,
    "col3": 0,
    "col4": null,
    "col5": 0
  },
  {
    "CoaCode": "740",
    "SortCode": 76,
    "Section": "Commitments",
    "RowDescription": "with risk grade 1",
    "RowType": "VAL",
    "SumType": null,
    "SumAccounts": null,
    "col1": 0,
    "col2": null,
    "col3": 0,
    "col4": null,
    "col5": 0
  },
  {
    "CoaCode": "750",
    "SortCode": 77,
    "Section": "Commitments",
    "RowDescription": "with risk grade 2",
    "RowType": "VAL",
    "SumType": null,
    "SumAccounts": null,
    "col1": 0,
    "col2": null,
    "col3": 0,
    "col4": null,
    "col5": 0
  },
  {
    "CoaCode": "760",
    "SortCode": 78,
    "Section": "Commitments",
    "RowDescription": "with risk grade 3",
    "RowType": "VAL",
    "SumType": null,
    "SumAccounts": null,
    "col1": 0,
    "col2": null,
    "col3": 0,
    "col4": null,
    "col5": 0
  },
  {
    "CoaCode": "770",
    "SortCode": 79,
    "Section": "Commitments",
    "RowDescription": "with risk grade 4",
    "RowType": "VAL",
    "SumType": null,
    "SumAccounts": null,
    "col1": 0,
    "col2": null,
    "col3": 0,
    "col4": null,
    "col5": 0
  },
  {
    "CoaCode": "780",
    "SortCode": 80,
    "Section": "Commitments",
    "RowDescription": "with risk grade 5",
    "RowType": "VAL",
    "SumType": null,
    "SumAccounts": null,
    "col1": 0,
    "col2": null,
    "col3": 0,
    "col4": null,
    "col5": 0
  },
  {
    "CoaCode": "790",
    "SortCode": 81,
    "Section": "Commitments",
    "RowDescription": "with risk grade 6",
    "RowType": "VAL",
    "SumType": null,
    "SumAccounts": null,
    "col1": 0,
    "col2": null,
    "col3": 0,
    "col4": null,
    "col5": 0
  },
  {
    "CoaCode": "8502 000",
    "SortCode": 82,
    "Section": "Commitments",
    "RowDescription": "Forward forward deposits",
    "RowType": "VAL",
    "SumType": null,
    "SumAccounts": null,
    "col1": 0,
    "col2": null,
    "col3": 0,
    "col4": null,
    "col5": 0
  },
  {
    "CoaCode": "810",
    "SortCode": 83,
    "Section": "Commitments",
    "RowDescription": "with risk grade 1",
    "RowType": "VAL",
    "SumType": null,
    "SumAccounts": null,
    "col1": 0,
    "col2": null,
    "col3": 0,
    "col4": null,
    "col5": 0
  },
  {
    "CoaCode": "820",
    "SortCode": 84,
    "Section": "Commitments",
    "RowDescription": "with risk grade 2",
    "RowType": "VAL",
    "SumType": null,
    "SumAccounts": null,
    "col1": 0,
    "col2": null,
    "col3": 0,
    "col4": null,
    "col5": 0
  },
  {
    "CoaCode": "830",
    "SortCode": 85,
    "Section": "Commitments",
    "RowDescription": "with risk grade 3",
    "RowType": "VAL",
    "SumType": null,
    "SumAccounts": null,
    "col1": 0,
    "col2": null,
    "col3": 0,
    "col4": null,
    "col5": 0
  },
  {
    "CoaCode": "840",
    "SortCode": 86,
    "Section": "Commitments",
    "RowDescription": "with risk grade 4",
    "RowType": "VAL",
    "SumType": null,
    "SumAccounts": null,
    "col1": 0,
    "col2": null,
    "col3": 0,
    "col4": null,
    "col5": 0
  },
  {
    "CoaCode": "850",
    "SortCode": 87,
    "Section": "Commitments",
    "RowDescription": "with risk grade 5",
    "RowType": "VAL",
    "SumType": null,
    "SumAccounts": null,
    "col1": 0,
    "col2": null,
    "col3": 0,
    "col4": null,
    "col5": 0
  },
  {
    "CoaCode": "860",
    "SortCode": 88,
    "Section": "Commitments",
    "RowDescription": "with risk grade 6",
    "RowType": "VAL",
    "SumType": null,
    "SumAccounts": null,
    "col1": 0,
    "col2": null,
    "col3": 0,
    "col4": null,
    "col5": 0
  },
  {
    "CoaCode": "8503 000",
    "SortCode": 89,
    "Section": "Commitments",
    "RowDescription": "partly-paid shares and securities",
    "RowType": "VAL",
    "SumType": null,
    "SumAccounts": null,
    "col1": 0,
    "col2": null,
    "col3": 0,
    "col4": null,
    "col5": 0
  },
  {
    "CoaCode": "880",
    "SortCode": 90,
    "Section": "Commitments",
    "RowDescription": "with risk grade 1",
    "RowType": "VAL",
    "SumType": null,
    "SumAccounts": null,
    "col1": 0,
    "col2": null,
    "col3": 0,
    "col4": null,
    "col5": 0
  },
  {
    "CoaCode": "890",
    "SortCode": 91,
    "Section": "Commitments",
    "RowDescription": "with risk grade 2",
    "RowType": "VAL",
    "SumType": null,
    "SumAccounts": null,
    "col1": 0,
    "col2": null,
    "col3": 0,
    "col4": null,
    "col5": 0
  },
  {
    "CoaCode": "900",
    "SortCode": 92,
    "Section": "Commitments",
    "RowDescription": "with risk grade 3",
    "RowType": "VAL",
    "SumType": null,
    "SumAccounts": null,
    "col1": 0,
    "col2": null,
    "col3": 0,
    "col4": null,
    "col5": 0
  },
  {
    "CoaCode": "910",
    "SortCode": 93,
    "Section": "Commitments",
    "RowDescription": "with risk grade 4",
    "RowType": "VAL",
    "SumType": null,
    "SumAccounts": null,
    "col1": 0,
    "col2": null,
    "col3": 0,
    "col4": null,
    "col5": 0
  },
  {
    "CoaCode": "920",
    "SortCode": 94,
    "Section": "Commitments",
    "RowDescription": "with risk grade 5",
    "RowType": "VAL",
    "SumType": null,
    "SumAccounts": null,
    "col1": 0,
    "col2": null,
    "col3": 0,
    "col4": null,
    "col5": 0
  },
  {
    "CoaCode": "930",
    "SortCode": 95,
    "Section": "Commitments",
    "RowDescription": "with risk grade 6",
    "RowType": "VAL",
    "SumType": null,
    "SumAccounts": null,
    "col1": 0,
    "col2": null,
    "col3": 0,
    "col4": null,
    "col5": 0
  },
  {
    "CoaCode": "8504 000",
    "SortCode": 96,
    "Section": "Commitments",
    "RowDescription": "Commitments with original maturity > 1 year",
    "RowType": "VAL",
    "SumType": null,
    "SumAccounts": null,
    "col1": 0,
    "col2": null,
    "col3": 0,
    "col4": null,
    "col5": 0
  },
  {
    "CoaCode": "950",
    "SortCode": 97,
    "Section": "Commitments",
    "RowDescription": "with risk grade 1",
    "RowType": "VAL",
    "SumType": null,
    "SumAccounts": null,
    "col1": 0,
    "col2": null,
    "col3": 0,
    "col4": null,
    "col5": 0
  },
  {
    "CoaCode": "960",
    "SortCode": 98,
    "Section": "Commitments",
    "RowDescription": "with risk grade 2",
    "RowType": "VAL",
    "SumType": null,
    "SumAccounts": null,
    "col1": 0,
    "col2": null,
    "col3": 0,
    "col4": null,
    "col5": 0
  },
  {
    "CoaCode": "970",
    "SortCode": 99,
    "Section": "Commitments",
    "RowDescription": "with risk grade 3",
    "RowType": "VAL",
    "SumType": null,
    "SumAccounts": null,
    "col1": 0,
    "col2": null,
    "col3": 0,
    "col4": null,
    "col5": 0
  },
  {
    "CoaCode": "980",
    "SortCode": 100,
    "Section": "Commitments",
    "RowDescription": "with risk grade 4",
    "RowType": "VAL",
    "SumType": null,
    "SumAccounts": null,
    "col1": 0,
    "col2": null,
    "col3": 0,
    "col4": null,
    "col5": 0
  },
  {
    "CoaCode": "990",
    "SortCode": 101,
    "Section": "Commitments",
    "RowDescription": "with risk grade 5",
    "RowType": "VAL",
    "SumType": null,
    "SumAccounts": null,
    "col1": 0,
    "col2": null,
    "col3": 0,
    "col4": null,
    "col5": 0
  },
  {
    "CoaCode": "1000",
    "SortCode": 102,
    "Section": "Commitments",
    "RowDescription": "with risk grade 6",
    "RowType": "VAL",
    "SumType": null,
    "SumAccounts": null,
    "col1": 0,
    "col2": null,
    "col3": 0,
    "col4": null,
    "col5": 0
  },
  {
    "CoaCode": "8505 000",
    "SortCode": 103,
    "Section": "Commitments",
    "RowDescription": "Commitments with original maturity up to 1 year",
    "RowType": "VAL",
    "SumType": null,
    "SumAccounts": null,
    "col1": 0,
    "col2": null,
    "col3": 0,
    "col4": null,
    "col5": 0
  },
  {
    "CoaCode": "1020",
    "SortCode": 104,
    "Section": "Commitments",
    "RowDescription": "with risk grade 1",
    "RowType": "VAL",
    "SumType": null,
    "SumAccounts": null,
    "col1": 0,
    "col2": null,
    "col3": 0,
    "col4": null,
    "col5": 0
  },
  {
    "CoaCode": "1030",
    "SortCode": 105,
    "Section": "Commitments",
    "RowDescription": "with risk grade 2",
    "RowType": "VAL",
    "SumType": null,
    "SumAccounts": null,
    "col1": 0,
    "col2": null,
    "col3": 0,
    "col4": null,
    "col5": 0
  },
  {
    "CoaCode": "1040",
    "SortCode": 106,
    "Section": "Commitments",
    "RowDescription": "with risk grade 3",
    "RowType": "VAL",
    "SumType": null,
    "SumAccounts": null,
    "col1": 0,
    "col2": null,
    "col3": 0,
    "col4": null,
    "col5": 0
  },
  {
    "CoaCode": "1050",
    "SortCode": 107,
    "Section": "Commitments",
    "RowDescription": "with risk grade 4",
    "RowType": "VAL",
    "SumType": null,
    "SumAccounts": null,
    "col1": 0,
    "col2": null,
    "col3": 0,
    "col4": null,
    "col5": 0
  },
  {
    "CoaCode": "1060",
    "SortCode": 108,
    "Section": "Commitments",
    "RowDescription": "with risk grade 5",
    "RowType": "VAL",
    "SumType": null,
    "SumAccounts": null,
    "col1": 0,
    "col2": null,
    "col3": 0,
    "col4": null,
    "col5": 0
  },
  {
    "CoaCode": "1070",
    "SortCode": 109,
    "Section": "Commitments",
    "RowDescription": "with risk grade 6",
    "RowType": "VAL",
    "SumType": null,
    "SumAccounts": null,
    "col1": 0,
    "col2": null,
    "col3": 0,
    "col4": null,
    "col5": 0
  },
  {
    "CoaCode": "8506 000",
    "SortCode": 110,
    "Section": "Unconditionally cancelable by the reporting institution without prior notice",
    "RowDescription": "Unconditionally cancelable by the reporting institution without prior notice",
    "RowType": "VAL",
    "SumType": null,
    "SumAccounts": null,
    "col1": 0,
    "col2": null,
    "col3": 0,
    "col4": null,
    "col5": 0
  },
  {
    "CoaCode": "2000",
    "SortCode": 111,
    "Section": "With automatic cancellation due to deterioration in borrowers' creditworthiness",
    "RowDescription": "With automatic cancellation due to deterioration in borrowers' creditworthiness",
    "RowType": "VAL",
    "SumType": null,
    "SumAccounts": null,
    "col1": 0,
    "col2": null,
    "col3": 0,
    "col4": null,
    "col5": 0
  },
  {
    "CoaCode": null,
    "SortCode": 112,
    "Section": "Commitments with certain drawdown",
    "RowDescription": "Commitments with certain drawdown",
    "RowType": "VAL",
    "SumType": null,
    "SumAccounts": null,
    "col1": 0,
    "col2": null,
    "col3": 0,
    "col4": null,
    "col5": 0
  },
  {
    "CoaCode": "2010",
    "SortCode": 113,
    "Section": "Commitments with certain drawdown",
    "RowDescription": "with risk grade 1",
    "RowType": "VAL",
    "SumType": null,
    "SumAccounts": null,
    "col1": 0,
    "col2": null,
    "col3": 0,
    "col4": null,
    "col5": 0
  },
  {
    "CoaCode": "2020",
    "SortCode": 114,
    "Section": "Commitments with certain drawdown",
    "RowDescription": "with risk grade 2",
    "RowType": "VAL",
    "SumType": null,
    "SumAccounts": null,
    "col1": 0,
    "col2": null,
    "col3": 0,
    "col4": null,
    "col5": 0
  },
  {
    "CoaCode": "2030",
    "SortCode": 115,
    "Section": "Commitments with certain drawdown",
    "RowDescription": "with risk grade 3",
    "RowType": "VAL",
    "SumType": null,
    "SumAccounts": null,
    "col1": 0,
    "col2": null,
    "col3": 0,
    "col4": null,
    "col5": 0
  },
  {
    "CoaCode": "2040",
    "SortCode": 116,
    "Section": "Commitments with certain drawdown",
    "RowDescription": "with risk grade 4",
    "RowType": "VAL",
    "SumType": null,
    "SumAccounts": null,
    "col1": 0,
    "col2": null,
    "col3": 0,
    "col4": null,
    "col5": 0
  },
  {
    "CoaCode": "2050",
    "SortCode": 117,
    "Section": "Commitments with certain drawdown",
    "RowDescription": "with risk grade 5",
    "RowType": "VAL",
    "SumType": null,
    "SumAccounts": null,
    "col1": 0,
    "col2": null,
    "col3": 0,
    "col4": null,
    "col5": 0
  },
  {
    "CoaCode": "2060",
    "SortCode": 118,
    "Section": "Commitments with certain drawdown",
    "RowDescription": "with risk grade 6",
    "RowType": "VAL",
    "SumType": null,
    "SumAccounts": null,
    "col1": 0,
    "col2": null,
    "col3": 0,
    "col4": null,
    "col5": 0
  },
  {
    "CoaCode": "8600 000",
    "SortCode": 119,
    "Section": "Commitments with certain drawdown",
    "RowDescription": "Pending Litigations",
    "RowType": "VAL",
    "SumType": null,
    "SumAccounts": null,
    "col1": 0,
    "col2": null,
    "col3": 0,
    "col4": null,
    "col5": 0
  },
  {
    "CoaCode": "8700 000",
    "SortCode": 120,
    "Section": "Performance Related Contingencies",
    "RowDescription": "Performance Related Contingencies",
    "RowType": "VAL",
    "SumType": null,
    "SumAccounts": null,
    "col1": 0,
    "col2": null,
    "col3": 0,
    "col4": null,
    "col5": 0
  },
  {
    "CoaCode": "3000",
    "SortCode": 121,
    "Section": "Performance Related Contingencies",
    "RowDescription": "with risk grade 1",
    "RowType": "VAL",
    "SumType": null,
    "SumAccounts": null,
    "col1": 0,
    "col2": null,
    "col3": 0,
    "col4": null,
    "col5": 0
  },
  {
    "CoaCode": "3010",
    "SortCode": 122,
    "Section": "Performance Related Contingencies",
    "RowDescription": "with risk grade 2",
    "RowType": "VAL",
    "SumType": null,
    "SumAccounts": null,
    "col1": 0,
    "col2": null,
    "col3": 0,
    "col4": null,
    "col5": 0
  },
  {
    "CoaCode": "3020",
    "SortCode": 123,
    "Section": "Performance Related Contingencies",
    "RowDescription": "with risk grade 3",
    "RowType": "VAL",
    "SumType": null,
    "SumAccounts": null,
    "col1": 0,
    "col2": null,
    "col3": 0,
    "col4": null,
    "col5": 0
  },
  {
    "CoaCode": "3030",
    "SortCode": 124,
    "Section": "Performance Related Contingencies",
    "RowDescription": "with risk grade 4",
    "RowType": "VAL",
    "SumType": null,
    "SumAccounts": null,
    "col1": 0,
    "col2": null,
    "col3": 0,
    "col4": null,
    "col5": 0
  },
  {
    "CoaCode": "3040",
    "SortCode": 125,
    "Section": "Performance Related Contingencies",
    "RowDescription": "with risk grade 5",
    "RowType": "VAL",
    "SumType": null,
    "SumAccounts": null,
    "col1": 0,
    "col2": null,
    "col3": 0,
    "col4": null,
    "col5": 0
  },
  {
    "CoaCode": "3050",
    "SortCode": 126,
    "Section": "Performance Related Contingencies",
    "RowDescription": "with risk grade 6",
    "RowType": "VAL",
    "SumType": null,
    "SumAccounts": null,
    "col1": 0,
    "col2": null,
    "col3": 0,
    "col4": null,
    "col5": 0
  },
  {
    "CoaCode": "8900 000",
    "SortCode": 127,
    "Section": "All Other Contingent Liabilities",
    "RowDescription": "All Other Contingent Liabilities",
    "RowType": "VAL",
    "SumType": null,
    "SumAccounts": null,
    "col1": 0,
    "col2": null,
    "col3": 0,
    "col4": null,
    "col5": 0
  }
]